{
"1": {
"time": " 75",
"real": "75.16",
"user": "72.94",
"sys": "1.75"
},
"2": {
"time": " 72",
"real": "72.72",
"user": "136.34",
"sys": "2.21"
},
"3": {
"time": " 73",
"real": "73.51",
"user": "204.06",
"sys": "3.09"
},
"4": {
"time": " 71",
"real": "71.94",
"user": "263.36",
"sys": "4.94"
},
"5": {
"time": " 70",
"real": "70.24",
"user": "318.42",
"sys": "7.71"
},
"6": {
"time": " 66",
"real": "66.68",
"user": "363.08",
"sys": "4.01"
},
"7": {
"time": " 71",
"real": "71.17",
"user": "453.50",
"sys": "4.12"
},
"8": {
"time": " 66",
"real": "67.03",
"user": "484.18",
"sys": "6.62"
},
"9": {
"time": " 63",
"real": "63.89",
"user": "516.25",
"sys": "5.97"
},
"10": {
"time": " 64",
"real": "64.20",
"user": "573.28",
"sys": "7.02"
},
"11": {
"time": " 65",
"real": "65.81",
"user": "647.43",
"sys": "8.93"
},
"12": {
"time": " 66",
"real": "66.84",
"user": "721.17",
"sys": "10.11"
},
"13": {
"time": " 64",
"real": "65.16",
"user": "757.58",
"sys": "7.03"
},
"14": {
"time": " 65",
"real": "65.36",
"user": "817.15",
"sys": "7.93"
},
"15": {
"time": " 63",
"real": "63.41",
"user": "852.39",
"sys": "8.68"
},
"16": {
"time": " 64",
"real": "64.88",
"user": "918.50",
"sys": "11.78"
},
"17": {
"time": " 63",
"real": "63.55",
"user": "961.56",
"sys": "14.41"
},
"18": {
"time": " 66",
"real": "67.00",
"user": "1071.21",
"sys": "16.68"
},
"19": {
"time": " 62",
"real": "63.05",
"user": "1065.20",
"sys": "9.80"
},
"20": {
"time": " 65",
"real": "65.87",
"user": "1178.00",
"sys": "12.50"
},
"21": {
"time": " 63",
"real": "63.78",
"user": "1173.46",
"sys": "26.55"
},
"22": {
"time": " 64",
"real": "64.23",
"user": "1236.88",
"sys": "24.13"
},
"23": {
"time": " 64",
"real": "64.29",
"user": "1309.89",
"sys": "15.00"
},
"24": {
"time": " 65",
"real": "65.39",
"user": "1394.63",
"sys": "16.36"
},
"25": {
"time": " 66",
"real": "66.58",
"user": "1467.79",
"sys": "18.52"
},
"26": {
"time": " 65",
"real": "66.15",
"user": "1508.41",
"sys": "33.50"
},
"27": {
"time": " 64",
"real": "65.19",
"user": "1537.37",
"sys": "30.45"
},
"28": {
"time": " 66",
"real": "66.36",
"user": "1631.91",
"sys": "25.09"
},
"29": {
"time": " 66",
"real": "66.79",
"user": "1705.74",
"sys": "27.72"
},
"30": {
"time": " 65",
"real": "65.71",
"user": "1718.20",
"sys": "26.30"
},
"31": {
"time": " 65",
"real": "66.23",
"user": "1795.72",
"sys": "24.38"
},
"32": {
"time": " 67",
"real": "68.16",
"user": "1920.22",
"sys": "25.36"
},
"33": {
"time": " 66",
"real": "66.25",
"user": "1907.57",
"sys": "35.83"
},
"34": {
"time": " 66",
"real": "66.43",
"user": "1965.09",
"sys": "44.78"
},
"35": {
"time": " 66",
"real": "66.43",
"user": "2017.94",
"sys": "36.51"
},
"36": {
"time": " 66",
"real": "66.35",
"user": "2076.92",
"sys": "28.69"
},
"37": {
"time": " 65",
"real": "65.48",
"user": "2091.30",
"sys": "42.95"
},
"38": {
"time": " 65",
"real": "65.58",
"user": "2172.44",
"sys": "31.22"
},
"39": {
"time": " 64",
"real": "64.82",
"user": "2190.24",
"sys": "31.03"
},
"40": {
"time": " 65",
"real": "66.15",
"user": "2297.73",
"sys": "25.15"
},
"41": {
"time": " 64",
"real": "64.59",
"user": "2291.94",
"sys": "37.79"
},
"42": {
"time": " 63",
"real": "63.57",
"user": "2308.96",
"sys": "35.08"
},
"43": {
"time": " 64",
"real": "64.53",
"user": "2394.82",
"sys": "32.38"
},
"44": {
"time": " 62",
"real": "63.12",
"user": "2384.76",
"sys": "34.29"
},
"45": {
"time": " 63",
"real": "63.32",
"user": "2470.33",
"sys": "24.43"
},
"46": {
"time": " 62",
"real": "63.05",
"user": "2493.03",
"sys": "30.34"
},
"47": {
"time": " 62",
"real": "62.64",
"user": "2483.35",
"sys": "40.20"
},
"48": {
"time": " 61",
"real": "61.55",
"user": "2499.47",
"sys": "41.30"
},
"49": {
"time": " 61",
"real": "61.73",
"user": "2557.65",
"sys": "33.10"
},
"50": {
"time": " 60",
"real": "60.37",
"user": "2552.66",
"sys": "33.99"
},
"51": {
"time": " 59",
"real": "60.04",
"user": "2603.21",
"sys": "30.39"
},
"52": {
"time": " 59",
"real": "60.24",
"user": "2637.24",
"sys": "44.62"
},
"53": {
"time": " 59",
"real": "59.57",
"user": "2643.61",
"sys": "37.72"
},
"54": {
"time": " 59",
"real": "59.32",
"user": "2674.76",
"sys": "39.58"
},
"55": {
"time": " 57",
"real": "58.14",
"user": "2690.83",
"sys": "34.11"
},
"56": {
"time": " 58",
"real": "58.88",
"user": "2737.40",
"sys": "36.79"
},
"57": {
"time": " 58",
"real": "58.39",
"user": "2728.46",
"sys": "45.31"
},
"58": {
"time": " 58",
"real": "58.65",
"user": "2803.61",
"sys": "32.33"
},
"59": {
"time": " 56",
"real": "56.77",
"user": "2747.62",
"sys": "29.42"
},
"60": {
"time": " 56",
"real": "56.61",
"user": "2799.50",
"sys": "44.54"
},
"61": {
"time": " 56",
"real": "56.96",
"user": "2884.85",
"sys": "26.38"
},
"62": {
"time": " 56",
"real": "56.52",
"user": "2850.68",
"sys": "40.60"
},
"63": {
"time": " 55",
"real": "56.06",
"user": "2844.57",
"sys": "39.98"
},
"64": {
"time": " 55",
"real": "55.61",
"user": "2857.64",
"sys": "45.75"
}
}
